pyrdfrules/__about__.py
pyrdfrules/__init__.py
pyrdfrules/application.py
pyrdfrules/common.py
pyrdfrules/config.py
pyrdfrules/api/__init__.py
pyrdfrules/api/http_api_urls.py
pyrdfrules/api/http_rdfrules_api.py
pyrdfrules/api/http_rdfrules_api_context.py
pyrdfrules/api/rdfrules_api.py
pyrdfrules/api/rdfrules_api_context.py
pyrdfrules/api/cache/__init__.py
pyrdfrules/api/cache/cache_api.py
pyrdfrules/api/cache/cache_http_api.py
pyrdfrules/api/task/__init__.py
pyrdfrules/api/task/task_api.py
pyrdfrules/api/task/task_http_api.py
pyrdfrules/api/task/exception/__init__.py
pyrdfrules/api/task/exception/task_not_found_exception.py
pyrdfrules/api/workspace/__init__.py
pyrdfrules/api/workspace/workspace_api.py
pyrdfrules/api/workspace/workspace_http_api.py
pyrdfrules/api/workspace/exception/__init__.py
pyrdfrules/api/workspace/exception/workspace_file_not_found_exception.py
pyrdfrules/common/__init__.py
pyrdfrules/common/event/__init__.py
pyrdfrules/common/event/event_dispatcher.py
pyrdfrules/common/exception/__init__.py
pyrdfrules/common/exception/pyrdfrules_exception.py
pyrdfrules/common/file/__init__.py
pyrdfrules/common/file/workspace.py
pyrdfrules/common/file/workspace_directory.py
pyrdfrules/common/file/workspace_file.py
pyrdfrules/common/file/workspace_item.py
pyrdfrules/common/file/workspace_tree.py
pyrdfrules/common/format/__init__.py
pyrdfrules/common/format/confusion_matrix.py
pyrdfrules/common/format/histogram.py
pyrdfrules/common/http/__init__.py
pyrdfrules/common/http/get_http_client.py
pyrdfrules/common/http/http_client.py
pyrdfrules/common/http/http_request.py
pyrdfrules/common/http/url.py
pyrdfrules/common/logging/__init__.py
pyrdfrules/common/logging/logger.py
pyrdfrules/common/result/__init__.py
pyrdfrules/common/result/evaluation.py
pyrdfrules/common/result/histogram.py
pyrdfrules/common/result/result.py
pyrdfrules/common/result/resultobject.py
pyrdfrules/common/rule/__init__.py
pyrdfrules/common/rule/resultrule.py
pyrdfrules/common/rule/ruleset.py
pyrdfrules-1.0.2.dist-info/METADATA
pyrdfrules-1.0.2.dist-info/WHEEL
pyrdfrules-1.0.2.dist-info/licenses/LICENSE
pyrdfrules-1.0.2.dist-info/RECORD
