Metadata-Version: 2.3
Name: pyrdfrules
Version: 1.0.2
Summary: Python wrapper for RDFRules.
Project-URL: Documentation, https://github.com/KIZI/pyrdfrules
Project-URL: Issues, https://github.com/KIZI/pyrdfrules/issues
Project-URL: Source, https://github.com/KIZI/pyrdfrules
Author-email: Karel Douda <kareldouda1@gmail.com>
License: MIT
Keywords: rdf,rdfrules,rules
Classifier: Development Status :: 4 - Beta
Classifier: Programming Language :: Python
Classifier: Programming Language :: Python :: 3.7
Classifier: Programming Language :: Python :: 3.8
Classifier: Programming Language :: Python :: 3.9
Classifier: Programming Language :: Python :: 3.10
Classifier: Programming Language :: Python :: 3.11
Classifier: Programming Language :: Python :: Implementation :: CPython
Classifier: Programming Language :: Python :: Implementation :: PyPy
Requires-Python: >=3.7
Requires-Dist: install-jdk==1.1.0
Requires-Dist: jpype1==1.5.0
Requires-Dist: pydantic==2.10.5
Requires-Dist: requests==2.32.3
Requires-Dist: rich==13.9.4
Requires-Dist: tqdm==4.67.1
